transcriptanalysis/__init__.py
transcriptanalysis/config_schemas.py
transcriptanalysis/configs/__init__.py
transcriptanalysis/configs/config.json
transcriptanalysis/configs/configA.json
transcriptanalysis/configs/configM.json
transcriptanalysis/configs/data_format_config.json
transcriptanalysis/data_handlers.py
transcriptanalysis/json_inputs/__init__.py
transcriptanalysis/json_inputs/news_articles.json
transcriptanalysis/json_inputs/teacher_transcript.json
transcriptanalysis/json_inputs/transcripts.json
transcriptanalysis/langchain_llm.py
transcriptanalysis/logging_config.py
transcriptanalysis/main.py
transcriptanalysis/prompts/__init__.py
transcriptanalysis/prompts/deductive.txt
transcriptanalysis/prompts/inductive.txt
transcriptanalysis/prompts/parse.txt
transcriptanalysis/qual_functions.py
transcriptanalysis/utils.py
transcriptanalysis/validator.py
transcriptanalysis-0.1.0.dist-info/METADATA
transcriptanalysis-0.1.0.dist-info/WHEEL
transcriptanalysis-0.1.0.dist-info/entry_points.txt
transcriptanalysis-0.1.0.dist-info/RECORD
