Metadata-Version: 2.3
Name: transcriptanalysis
Version: 0.1.0
Summary: Middle LLC.
Author: Your Name
Author-email: your.email@example.com
Requires-Python: >=3.10,<4.0
Classifier: Programming Language :: Python :: 3
Classifier: Programming Language :: Python :: 3.10
Classifier: Programming Language :: Python :: 3.11
Classifier: Programming Language :: Python :: 3.12
Classifier: Programming Language :: Python :: 3.13
Requires-Dist: hdbscan
Requires-Dist: huggingface-hub
Requires-Dist: jsonschema
Requires-Dist: langchain
Requires-Dist: langchain-openai
Requires-Dist: matplotlib
Requires-Dist: numpy
Requires-Dist: pandas
Requires-Dist: pydantic
Requires-Dist: pytest
Requires-Dist: scikit-learn
Requires-Dist: scipy
Requires-Dist: tqdm
Requires-Dist: umap
Requires-Dist: umap-learn
